biscuit/__init__.py
biscuit/api.py
biscuit/middleware.py
examples/__init__.py
examples/basic_app.py
tests/__init__.py
tests/conftest.py
tests/test_api.py
tests/test_app.py
tests/test_biscuit.py
biscuit-0.0.1.dist-info/METADATA
biscuit-0.0.1.dist-info/WHEEL
biscuit-0.0.1.dist-info/top_level.txt
biscuit-0.0.1.dist-info/RECORD
